mygeometry/__init__.py
mygeometry/circle.py
mygeometry/rectangle.py
myBZgeometry-0.1.dist-info/METADATA
myBZgeometry-0.1.dist-info/WHEEL
myBZgeometry-0.1.dist-info/top_level.txt
myBZgeometry-0.1.dist-info/RECORD
