Metadata-Version: 2.2
Name: myBZgeometry
Version: 0.1
Summary: A simple Python library for calculating geometric areas
Home-page: https://github.com/bhushanzade02/mygeometry
Author: Your Name
Author-email: bhushanzade02@gmail.com
Classifier: Programming Language :: Python :: 3
Classifier: License :: OSI Approved :: MIT License
Classifier: Operating System :: OS Independent
Requires-Python: >=3.6
Dynamic: author
Dynamic: author-email
Dynamic: classifier
Dynamic: home-page
Dynamic: requires-python
Dynamic: summary
